wavemqtt/__init__.py
wavemqtt/wavemqtt.py
wavemqtt-0.0.4.dist-info/METADATA
wavemqtt-0.0.4.dist-info/RECORD
wavemqtt-0.0.4.dist-info/WHEEL
wavemqtt-0.0.4.dist-info/top_level.txt
